xarrayuvecs/__init__.py
xarrayuvecs/lut2d.py
xarrayuvecs/odfplot.py
xarrayuvecs/uniform_dist.py
xarrayuvecs/uvecs.py
xarrayuvecs-0.1.12.dist-info/LICENSE
xarrayuvecs-0.1.12.dist-info/METADATA
xarrayuvecs-0.1.12.dist-info/WHEEL
xarrayuvecs-0.1.12.dist-info/top_level.txt
xarrayuvecs-0.1.12.dist-info/RECORD
